{
  "revenue": {
    "2021": 214.02,
    "2022": 1256,
    "2023": 241.81,
    "2024": 1781,
    "2025": 1583
  },
  "gross_profit": {
    "2021": 119.83,
    "2022": 329.36,
    "2023": 132.32,
    "2024": 442.83,
    "2025": 90.02
  },
  "operating_income": {
    "2021": -84.84,
    "2022": 115.93,
    "2023": -168.63,
    "2024": 164.97,
    "2025": -316.3
  },
  "net_income": {
    "2021": -98.41,
    "2022": -725.48,
    "2023": -1732,
    "2024": 980.89,
    "2025": -317.77
  },
  "eps": {
    "2021": -0.35,
    "2022": -2.6,
    "2023": -6.21,
    "2024": 3.52,
    "2025": -1.14
  },
  "interest_expense": {
    "2021": 134.14,
    "2022": 155.98,
    "2023": 182.38,
    "2024": 246.77,
    "2025": 269.02
  }
}