{
  "as_of": "2026-06-24",
  "bars": 1237,
  "close": 32.04,
  "sma_20": 28.568,
  "sma_50": 27.727000000000004,
  "sma_200": 32.65705,
  "ema_20": 29.28145557437866,
  "ema_50": 27.929147314910416,
  "ema_100": 28.579719662845992,
  "ema_200": 30.704966373498713,
  "obv": 1857799546.0,
  "weekly_trend": "Up",
  "monthly_trend": "Up",
  "support_resistance": {
    "price": 32.04,
    "nearest_resistance": 34.88,
    "nearest_support": 26.01,
    "resistance_levels": [
      34.88,
      36.8
    ],
    "support_levels": [
      26.01,
      24.89,
      23.8
    ]
  },
  "rsi_14": 67.27029182373649,
  "macd": 1.464013282953708,
  "macd_signal": 0.9363560065935245,
  "macd_hist": 0.5276572763601836,
  "adx_14": 23.212371843996895,
  "plus_di": 35.950878687765986,
  "minus_di": 15.801650534587958,
  "atr_14": 1.2790210114842147,
  "bb_upper": 33.126638393204644,
  "bb_lower": 24.00936160679536,
  "week52_high": 46.88,
  "week52_low": 19.11,
  "rsi_divergence": {
    "type": null
  },
  "patterns": [
    {
      "name": "Symmetrical Triangle",
      "type": "neutral",
      "confidence": 0.45,
      "status": "forming",
      "neckline": null,
      "target": null,
      "note": "Converging highs and lows; breakout direction undecided."
    }
  ]
}