{
  "symbol": "AMTEX",
  "income_statement_annual": {
    "revenue": {
      "2021": 1075,
      "2022": 1251,
      "2023": 1692,
      "2024": 2793,
      "2025": 2371
    },
    "gross_profit": {
      "2021": 9.47,
      "2022": 216.75,
      "2023": 123.85,
      "2024": 421.39,
      "2025": 132.67
    },
    "operating_income": {
      "2021": -94.21,
      "2022": 105.27,
      "2023": -82.92,
      "2024": 325.16,
      "2025": -34.75
    },
    "net_income": {
      "2021": -147.91,
      "2022": 103.49,
      "2023": 137.91,
      "2024": 179.03,
      "2025": -130.15
    },
    "eps": {
      "2021": -0.57,
      "2022": 0.4,
      "2023": 0.53,
      "2024": 0.69,
      "2025": -0.5
    },
    "interest_expense": {
      "2021": 88.8,
      "2022": 77.63,
      "2023": 54.73,
      "2024": 98.96,
      "2025": 83.33
    }
  },
  "balance_sheet_annual": {
    "current_assets": {
      "2021": 1136,
      "2022": 1219,
      "2023": 1084,
      "2024": 1420,
      "2025": 1637
    },
    "cash_and_equivalents": {
      "2021": 149.64,
      "2022": 82.72,
      "2023": 112.09,
      "2024": 118.25,
      "2025": 92.01
    },
    "inventory": {
      "2021": 650.86,
      "2022": 637.1,
      "2023": 435.07,
      "2024": 715.59,
      "2025": 848.26
    },
    "total_assets": {
      "2021": 3577,
      "2022": 3661,
      "2023": 3310,
      "2024": 3685,
      "2025": 3540
    },
    "current_liabilities": {
      "2021": 11216,
      "2022": 11035,
      "2023": 10479,
      "2024": 9330,
      "2025": 9174
    },
    "total_liabilities": {
      "2021": 12775,
      "2022": 12754,
      "2023": 11944,
      "2024": 12141,
      "2025": 12125
    },
    "total_debt": {
      "2021": 8536,
      "2022": 8466,
      "2023": 7473,
      "2024": 7292,
      "2025": 7257
    },
    "total_equity": {
      "2021": -9198,
      "2022": -9093,
      "2023": -8634,
      "2024": -8457,
      "2025": -8585
    }
  },
  "cashflow_annual": {
    "cash_from_operations": {
      "2021": 46.32,
      "2022": -16.07,
      "2023": 249.02,
      "2024": 453.96,
      "2025": -274.69
    },
    "cash_from_investing": {
      "2021": -11.33,
      "2022": 19.52,
      "2023": 773.56,
      "2024": -47.3,
      "2025": 396.28
    },
    "cash_from_financing": {
      "2021": -60.2,
      "2022": -70.37,
      "2023": -993.21,
      "2024": -400.5,
      "2025": -147.84
    },
    "capex": {
      "2021": 35.5,
      "2022": 20.55,
      "2023": 27.53,
      "2024": 101.8,
      "2025": 32.62
    }
  },
  "income_statement_quarterly": {
    "revenue": {
      "2026-03": 659.06,
      "2025-12": 859.79,
      "2025-09": 925.48,
      "2025-06": 546.79,
      "2025-03": 400.63,
      "2024-12": 736.39,
      "2024-09": 686.98,
      "2024-06": 704.91,
      "2024-03": 661.01,
      "2023-12": 701.45,
      "2023-09": 725.74,
      "2023-06": 581.85,
      "2023-03": 430.62,
      "2022-12": 323.71,
      "2022-09": 355.36,
      "2022-06": 401.72,
      "2022-03": 265.12,
      "2021-12": 299.18,
      "2021-09": 284.86,
      "2021-06": 225.94
    },
    "gross_profit": {
      "2026-03": 18.27,
      "2025-12": 148.32,
      "2025-09": 120.22,
      "2025-06": -46.46,
      "2025-03": 65.82,
      "2024-12": 12.24,
      "2024-09": 101.07,
      "2024-06": 127.67,
      "2024-03": 81.92,
      "2023-12": 104.71,
      "2023-09": 107.09,
      "2023-06": 2.87,
      "2023-03": 2.45,
      "2022-12": 44.22,
      "2022-09": 74.31,
      "2022-06": 124.12,
      "2022-03": 45.24,
      "2021-12": 24.78,
      "2021-09": 22.62,
      "2021-06": -31.11
    },
    "operating_income": {
      "2026-03": -31.13,
      "2025-12": 95.24,
      "2025-09": 50.39,
      "2025-06": -41.23,
      "2025-03": -9.57,
      "2024-12": -12.1,
      "2024-09": 58.07,
      "2024-06": 189.78,
      "2024-03": 33.17,
      "2023-12": 43.14,
      "2023-09": 59.06,
      "2023-06": -112.61,
      "2023-03": -30.9,
      "2022-12": 7.62,
      "2022-09": 47.1,
      "2022-06": 101.92,
      "2022-03": 16.28,
      "2021-12": -3.66,
      "2021-09": -3.34,
      "2021-06": -63.18
    },
    "net_income": {
      "2026-03": -60.92,
      "2025-12": 60.57,
      "2025-09": 10.35,
      "2025-06": -36.5,
      "2025-03": -62.61,
      "2024-12": -38.02,
      "2024-09": 6.98,
      "2024-06": 146.3,
      "2024-03": 10.14,
      "2023-12": -11.42,
      "2023-09": 34,
      "2023-06": -84.33,
      "2023-03": -37.52,
      "2022-12": -30,
      "2022-09": 289.77,
      "2022-06": 139.51,
      "2022-03": -1.65,
      "2021-12": -9.61,
      "2021-09": -24.75,
      "2021-06": -53.53
    },
    "eps": {
      "2026-03": -0.23,
      "2025-12": 0.23,
      "2025-09": 0.04,
      "2025-06": -0.14,
      "2025-03": -0.24,
      "2024-12": -0.15,
      "2024-09": 0.03,
      "2024-06": 0.52,
      "2024-03": 0.04,
      "2023-12": -0.04,
      "2023-09": 0.14,
      "2023-06": -0.32,
      "2023-03": -0.14,
      "2022-12": -0.12,
      "2022-09": 1.12,
      "2022-06": 0.52,
      "2022-03": -0.01,
      "2021-12": -0.04,
      "2021-09": -0.1,
      "2021-06": -0.21
    },
    "interest_expense": {
      "2026-03": 21.55,
      "2025-12": 23.92,
      "2025-09": 28.47,
      "2025-03": 49.15,
      "2024-12": 18.46,
      "2024-09": 43.91,
      "2024-06": 8.23,
      "2024-03": 28.59,
      "2023-12": 44.58,
      "2023-09": 17.56,
      "2023-06": 12.11,
      "2023-03": 6.57,
      "2022-12": 19.72,
      "2022-09": 16.33,
      "2022-06": 18.17,
      "2022-03": 19.24,
      "2021-12": 20.29,
      "2021-09": 19.93,
      "2021-06": 12.96
    }
  },
  "balance_sheet_quarterly": {
    "current_assets": {
      "2026-03": 1594,
      "2025-12": 1673,
      "2025-09": 1783,
      "2025-06": 1637,
      "2025-03": 1494,
      "2024-12": 1589,
      "2024-09": 1478,
      "2024-06": 1420,
      "2024-03": 1160,
      "2023-12": 1224,
      "2023-09": 1165,
      "2023-06": 1084,
      "2023-03": 1221,
      "2022-12": 1236,
      "2022-09": 1273,
      "2022-06": 1219,
      "2022-03": 1198,
      "2021-12": 1207,
      "2021-09": 1143,
      "2021-06": 1136
    },
    "cash_and_equivalents": {
      "2026-03": 185.13,
      "2025-12": 137.25,
      "2025-09": 98.5,
      "2025-06": 92.01,
      "2025-03": 72.4,
      "2024-12": 142.14,
      "2024-09": 84.18,
      "2024-06": 118.25,
      "2024-03": 43.61,
      "2023-12": 60.78,
      "2023-09": 105.7,
      "2023-06": 112.09,
      "2023-03": 134.95,
      "2022-12": 122.89,
      "2022-09": 155.1,
      "2022-06": 82.72,
      "2022-03": 148.99,
      "2021-12": 119.5,
      "2021-09": 132.7,
      "2021-06": 149.64
    },
    "inventory": {
      "2026-03": 749.07,
      "2025-12": 690.45,
      "2025-09": 793.96,
      "2025-06": 848.26,
      "2025-03": 862.53,
      "2024-12": 802.77,
      "2024-09": 756.32,
      "2024-06": 715.59,
      "2024-03": 557.09,
      "2023-12": 547.2,
      "2023-09": 380.63,
      "2023-06": 435.07,
      "2023-03": 576.94,
      "2022-12": 632.25,
      "2022-09": 655.96,
      "2022-06": 637.1,
      "2022-03": 637.78,
      "2021-12": 624.85,
      "2021-09": 617.62,
      "2021-06": 650.86
    },
    "total_assets": {
      "2026-03": 3565,
      "2025-12": 3642,
      "2025-09": 3668,
      "2025-06": 3540,
      "2025-03": 3495,
      "2024-12": 3677,
      "2024-09": 3643,
      "2024-06": 3685,
      "2024-03": 3429,
      "2023-12": 3456,
      "2023-09": 3388,
      "2023-06": 3310,
      "2023-03": 3126,
      "2022-12": 3129,
      "2022-09": 3167,
      "2022-06": 3661,
      "2022-03": 3599,
      "2021-12": 3619,
      "2021-09": 3570,
      "2021-06": 3577
    },
    "current_liabilities": {
      "2026-03": 9172,
      "2025-12": 9212,
      "2025-09": 9342,
      "2025-06": 9174,
      "2025-03": 9117,
      "2024-12": 9286,
      "2024-09": 9451,
      "2024-06": 9330,
      "2024-03": 9310,
      "2023-12": 9401,
      "2023-09": 9282,
      "2023-06": 10479,
      "2023-03": 10429,
      "2022-12": 10396,
      "2022-09": 10433,
      "2022-06": 11035,
      "2022-03": 11298,
      "2021-12": 11313,
      "2021-09": 11244,
      "2021-06": 11216
    },
    "total_liabilities": {
      "2026-03": 12057,
      "2025-12": 12073,
      "2025-09": 12242,
      "2025-06": 12125,
      "2025-03": 12133,
      "2024-12": 12252,
      "2024-09": 12180,
      "2024-06": 12141,
      "2024-03": 12029,
      "2023-12": 12046,
      "2023-09": 11987,
      "2023-06": 11944,
      "2023-03": 11997,
      "2022-12": 11962,
      "2022-09": 11970,
      "2022-06": 12754,
      "2022-03": 12833,
      "2021-12": 12852,
      "2021-09": 12793,
      "2021-06": 12775
    },
    "total_debt": {
      "2026-03": 7037,
      "2025-12": 7056,
      "2025-09": 7059,
      "2025-06": 7257,
      "2025-03": 6847,
      "2024-12": 6913,
      "2024-09": 7040,
      "2024-06": 7292,
      "2024-03": 7090,
      "2023-12": 7193,
      "2023-09": 7363,
      "2023-06": 7473,
      "2023-03": 7567,
      "2022-12": 7632,
      "2022-09": 7626,
      "2022-06": 8466,
      "2022-03": 8527,
      "2021-12": 8527,
      "2021-09": 8534,
      "2021-06": 8536
    },
    "total_equity": {
      "2026-03": -8492,
      "2025-12": -8431,
      "2025-09": -8574,
      "2025-06": -8585,
      "2025-03": -8638,
      "2024-12": -8575,
      "2024-09": -8537,
      "2024-06": -8457,
      "2024-03": -8601,
      "2023-12": -8591,
      "2023-09": -8600,
      "2023-06": -8634,
      "2023-03": -8871,
      "2022-12": -8833,
      "2022-09": -8803,
      "2022-06": -9093,
      "2022-03": -9234,
      "2021-12": -9232,
      "2021-09": -9223,
      "2021-06": -9198
    }
  },
  "cashflow_quarterly": {
    "cash_from_operations": {
      "2026-03": 80.27,
      "2025-12": 52.98,
      "2025-09": 6.43,
      "2025-06": -191.4,
      "2025-03": -20.98,
      "2024-12": 47.51,
      "2024-09": -109.82,
      "2024-06": 306.9,
      "2024-03": 33.61,
      "2023-12": 4.82,
      "2023-09": 108.62,
      "2023-06": 77,
      "2023-03": 96.88,
      "2022-12": -35.18,
      "2022-09": 110.32,
      "2022-06": -5.05,
      "2022-03": 29.51,
      "2021-12": -22.14,
      "2021-09": -18.38,
      "2021-06": 10.19
    },
    "cash_from_investing": {
      "2026-03": -13.33,
      "2025-12": -11.19,
      "2025-09": 8.85,
      "2025-06": 133.85,
      "2025-03": 51.81,
      "2024-12": 102.38,
      "2024-09": 108.24,
      "2024-06": -214.76,
      "2024-03": 52.21,
      "2023-12": 120.26,
      "2023-09": -5.01,
      "2023-06": -5.56,
      "2023-03": -19.63,
      "2022-12": -3.13,
      "2022-09": 801.89,
      "2022-06": -0.22,
      "2022-03": -0.02,
      "2021-12": 16.44,
      "2021-09": 3.32,
      "2021-06": -6.25
    },
    "cash_from_financing": {
      "2026-03": -19.06,
      "2025-12": -3.03,
      "2025-09": -8.79,
      "2025-06": 77.16,
      "2025-03": -100.58,
      "2024-12": -91.92,
      "2024-09": -32.5,
      "2024-06": -17.5,
      "2024-03": -103,
      "2023-12": -170,
      "2023-09": -110,
      "2023-06": -94.3,
      "2023-03": -65.2,
      "2022-12": 6.11,
      "2022-09": -839.83,
      "2022-06": -61,
      "2021-12": -7.5,
      "2021-09": -1.88,
      "2021-06": -32.77
    },
    "capex": {
      "2026-03": 13.33,
      "2025-12": 11.53,
      "2025-06": 7.89,
      "2025-03": 24.73,
      "2024-06": 9.6,
      "2024-03": 47.79,
      "2023-12": 58.6,
      "2023-09": 5.01,
      "2023-06": 1.65,
      "2023-03": 19.63,
      "2022-12": 3.13,
      "2022-09": 3.11,
      "2022-06": 0.22,
      "2022-03": 0.02,
      "2021-12": 18.56,
      "2021-09": 1.75,
      "2021-06": 11.69
    }
  },
  "ratios": {
    "pe_ratio": null,
    "price_to_book": -0.14,
    "roe": 0.0152,
    "roa": -0.0368,
    "gross_margin": 0.056,
    "industry_pe": null
  },
  "earnings": {
    "source": "stockanalysis.com (statistics + quarterly)",
    "as_of": "2026-06-28",
    "latest_eps": -0.23,
    "eps_ttm": null,
    "next_earnings_date": "Oct 2, 2026",
    "history": [
      {
        "period_end": "Mar 2026",
        "eps": -0.23,
        "eps_forecast": null,
        "eps_surprise_pct": null
      },
      {
        "period_end": "Dec 2025",
        "eps": 0.23,
        "eps_forecast": null,
        "eps_surprise_pct": null
      },
      {
        "period_end": "Sep 2025",
        "eps": 0.04,
        "eps_forecast": null,
        "eps_surprise_pct": null
      },
      {
        "period_end": "Jun 2025",
        "eps": -0.14,
        "eps_forecast": null,
        "eps_surprise_pct": null
      },
      {
        "period_end": "Mar 2025",
        "eps": -0.24,
        "eps_forecast": null,
        "eps_surprise_pct": null
      },
      {
        "period_end": "Dec 2024",
        "eps": -0.15,
        "eps_forecast": null,
        "eps_surprise_pct": null
      },
      {
        "period_end": "Sep 2024",
        "eps": 0.03,
        "eps_forecast": null,
        "eps_surprise_pct": null
      },
      {
        "period_end": "Jun 2024",
        "eps": 0.52,
        "eps_forecast": null,
        "eps_surprise_pct": null
      }
    ]
  },
  "dividends": {
    "source": "stockanalysis.com (statistics + dividend page)",
    "as_of": "2026-06-28",
    "yield": null,
    "per_share_ttm": null,
    "payout_ratio": null,
    "history": []
  },
  "overview": {
    "company_name": "Amtex Limited",
    "sector": "Non-compliant Textile Spinning",
    "industry": "Non-compliant Textile Spinning",
    "market_cap": 1193.4,
    "shares_outstanding": 259.43,
    "current_price": 4.59,
    "currency": "PKR"
  },
  "profile": {},
  "ownership": {},
  "announcements": {},
  "insider": {},
  "shareholding": {},
  "fipi": {},
  "monthly_sales": {}
}