{
  "current_assets": {
    "2021": 2812,
    "2022": 3682,
    "2023": 2494,
    "2024": 2689,
    "2025": 2460
  },
  "cash_and_equivalents": {
    "2021": 25.17,
    "2022": 30.37,
    "2023": 31.32,
    "2024": 81.27,
    "2025": 38.61
  },
  "inventory": {
    "2021": 1458,
    "2022": 1674,
    "2023": 1121,
    "2024": 1023,
    "2025": 850.44
  },
  "total_assets": {
    "2021": 8404,
    "2022": 9112,
    "2023": 6845,
    "2024": 6638,
    "2025": 6338
  },
  "current_liabilities": {
    "2021": 3011,
    "2022": 3838,
    "2023": 3753,
    "2024": 3637,
    "2025": 3744
  },
  "total_liabilities": {
    "2021": 4337,
    "2022": 5151,
    "2023": 4679,
    "2024": 4185,
    "2025": 3809
  },
  "total_debt": {
    "2021": 3716,
    "2022": 3946,
    "2023": 3584,
    "2024": 2708,
    "2025": 2311
  },
  "total_equity": {
    "2021": 4067,
    "2022": 3961,
    "2023": 2166,
    "2024": 2453,
    "2025": 2529
  }
}