{
  "revenue": {
    "2021": 2111,
    "2022": 2342,
    "2023": 2785,
    "2024": 3215,
    "2025": 1832
  },
  "gross_profit": {
    "2021": 707.29,
    "2022": 809.48,
    "2023": 1069,
    "2024": 1414,
    "2025": 703.18
  },
  "operating_income": {
    "2021": 9.01,
    "2022": 42.76,
    "2023": 172.67,
    "2024": 431.33,
    "2025": 107.72
  },
  "net_income": {
    "2021": -58.35,
    "2022": 113.64,
    "2023": -160.88,
    "2024": 5.35,
    "2025": 13.87
  },
  "eps": {
    "2021": -0.31,
    "2022": 0.61,
    "2023": -0.86,
    "2024": 0.03,
    "2025": 0.07
  },
  "interest_expense": {
    "2021": 385.51,
    "2022": 308.14,
    "2023": 553.93,
    "2024": 543.79,
    "2025": 342.85
  }
}