{
  "revenue": {
    "2021": 6260,
    "2022": 16518,
    "2023": 20200,
    "2024": 22319,
    "2025": 21413
  },
  "gross_profit": {
    "2021": 244.63,
    "2022": 1154,
    "2023": 375.64,
    "2024": 338.61,
    "2025": 1465
  },
  "operating_income": {
    "2021": -278.99,
    "2022": 18.52,
    "2023": -523.02,
    "2024": -636.72,
    "2025": 337.63
  },
  "net_income": {
    "2021": -666.44,
    "2022": -703.03,
    "2023": -586.31,
    "2024": -509.71,
    "2025": -967.79
  },
  "eps": {
    "2021": -1.38,
    "2022": -1.45,
    "2023": -1.21,
    "2024": -1.05,
    "2025": -2
  },
  "interest_expense": {
    "2021": 1.8
  }
}